nltk-stubs/py.typed
nltk-stubs/tree/tree.pyi
nltk_tree_ext/__init__.py
nltk_tree_ext/funcs.py
nltk_tree_ext/patch.py
nltk_tree_extensions-3.7.0.3.0.dist-info/LICENSE.txt
nltk_tree_extensions-3.7.0.3.0.dist-info/METADATA
nltk_tree_extensions-3.7.0.3.0.dist-info/WHEEL
nltk_tree_extensions-3.7.0.3.0.dist-info/RECORD
