Metadata-Version: 2.1
Name: nltk-tree-extensions
Version: 3.7.0.3.0
Summary: An extension module for nltk.tree
Home-page: https://pypi.com/project/nltk-tree-extensions
License: Apache-2.0
Author: Nori Hayashi
Author-email: net@hayashi-lin.net
Requires-Python: >=3.11,<4.0
Classifier: License :: OSI Approved :: Apache Software License
Classifier: Programming Language :: Python :: 3
Classifier: Programming Language :: Python :: 3.11
Classifier: Programming Language :: Python :: 3.12
Requires-Dist: nltk (>=3.7,<4.0)
Requires-Dist: rapidfuzz (>=3.7.0,<4.0.0)
Project-URL: Repository, https://github.com/aslemen/nltk-tree-extensions
